rustybt/__init__.py
rustybt/__main__.py
rustybt/_protocol.c
rustybt/_protocol.cpython-312-darwin.so
rustybt/_protocol.cpython-313-darwin.so
rustybt/_protocol.pxd
rustybt/_protocol.pyx
rustybt/_version.py
rustybt/algorithm.py
rustybt/api.py
rustybt/api.pyi
rustybt/country.py
rustybt/currency.py
rustybt/dispatch.py
rustybt/errors.py
rustybt/exceptions.py
rustybt/extensions.py
rustybt/protocol.py
rustybt/py.typed
rustybt/test_algorithms.py
rustybt/zipline_warnings.py
rustybt/analytics/__init__.py
rustybt/analytics/attribution.py
rustybt/analytics/notebook.py
rustybt/analytics/reports.py
rustybt/analytics/risk.py
rustybt/analytics/trade_analysis.py
rustybt/analytics/visualization.py
rustybt/assets/__init__.py
rustybt/assets/_assets.c
rustybt/assets/_assets.cpython-312-darwin.so
rustybt/assets/_assets.cpython-313-darwin.so
rustybt/assets/_assets.pxd
rustybt/assets/_assets.pyx
rustybt/assets/asset_db_migrations.py
rustybt/assets/asset_db_schema.py
rustybt/assets/asset_writer.py
rustybt/assets/assets.py
rustybt/assets/continuous_futures.c
rustybt/assets/continuous_futures.cpython-312-darwin.so
rustybt/assets/continuous_futures.cpython-313-darwin.so
rustybt/assets/continuous_futures.pyx
rustybt/assets/exchange_info.py
rustybt/assets/futures.py
rustybt/assets/roll_finder.py
rustybt/assets/synthetic.py
rustybt/backtest/__init__.py
rustybt/backtest/artifact_manager.py
rustybt/backtest/code_capture.py
rustybt/benchmarks/__init__.py
rustybt/benchmarks/comparisons.py
rustybt/benchmarks/exceptions.py
rustybt/benchmarks/models.py
rustybt/benchmarks/profiling.py
rustybt/benchmarks/reporter.py
rustybt/benchmarks/sequential.py
rustybt/benchmarks/threshold.py
rustybt/config/cache_freshness.yaml
rustybt/data/__init__.py
rustybt/data/_adjustments.c
rustybt/data/_adjustments.cpython-312-darwin.so
rustybt/data/_adjustments.cpython-313-darwin.so
rustybt/data/_adjustments.pyx
rustybt/data/_equities.c
rustybt/data/_equities.cpython-312-darwin.so
rustybt/data/_equities.cpython-313-darwin.so
rustybt-0.3.3.dist-info/licenses/LICENSE
rustybt-0.3.3.dist-info/METADATA
rustybt-0.3.3.dist-info/WHEEL
rustybt-0.3.3.dist-info/entry_points.txt
rustybt-0.3.3.dist-info/top_level.txt
rustybt-0.3.3.dist-info/RECORD
