Metadata-Version: 2.4
Name: rustybt
Version: 0.3.3
Summary: Modern Python backtesting engine built on Zipline-Reloaded, enhanced with Decimal precision, Polars data engine, and live trading capabilities
Author: Quantopian Inc, Stefan Jansen
Author-email: pm@ml4trading.io
Maintainer: RustyBT Contributors
License-Expression: Apache-2.0
Project-URL: homepage, https://github.com/jerryinyang/rustybt
Project-URL: repository, https://github.com/jerryinyang/rustybt
Project-URL: documentation, https://jerryinyang.github.io/rustybt/
Classifier: Development Status :: 4 - Beta
Classifier: Natural Language :: English
Classifier: Programming Language :: Python
Classifier: Programming Language :: Python :: 3.12
Classifier: Programming Language :: Python :: 3.13
Classifier: Operating System :: OS Independent
Classifier: Intended Audience :: Science/Research
Classifier: Topic :: Office/Business :: Financial :: Investment
Classifier: Topic :: Scientific/Engineering :: Information Analysis
Classifier: Topic :: System :: Distributed Computing
Requires-Python: >=3.12
License-File: LICENSE
Requires-Dist: numpy<2.0,>=1.26.0; python_version == "3.12"
Requires-Dist: numpy>=2.1; python_version >= "3.13"
Requires-Dist: pandas<3.0,>=1.3.0
Requires-Dist: alembic>=0.7.7
Requires-Dist: bcolz-zipline>=1.2.6
Requires-Dist: bottleneck>=1.0.0
Requires-Dist: click>=4.0.0
Requires-Dist: empyrical-reloaded>=0.5.7
Requires-Dist: intervaltree>=2.1.0
Requires-Dist: iso3166>=2.1.1
Requires-Dist: iso4217>=1.6.20180829
Requires-Dist: lru-dict>=1.1.4
Requires-Dist: multipledispatch>=0.6.0
Requires-Dist: networkx>=2.0
Requires-Dist: numexpr<2.10,>=2.8.0; python_version == "3.12"
Requires-Dist: numexpr>=2.10; python_version >= "3.13"
Requires-Dist: patsy>=0.4.0
Requires-Dist: python-dateutil>=2.4.2
Requires-Dist: pytz>=2018.5
Requires-Dist: requests>=2.9.1
Requires-Dist: scipy>=0.17.1
Requires-Dist: six>=1.10.0
Requires-Dist: sqlalchemy>=2
Requires-Dist: statsmodels>=0.6.1
Requires-Dist: toolz>=0.8.2
Requires-Dist: exchange-calendars>=4.2.4
Requires-Dist: polars>=1.0
Requires-Dist: pyarrow>=18.0
Requires-Dist: structlog
Requires-Dist: pydantic>=2.0
Requires-Dist: pyyaml>=6.0
Requires-Dist: ccxt>=4.0.0
Requires-Dist: yfinance>=0.2.0
Requires-Dist: apscheduler>=3.0
Requires-Dist: ib-insync>=0.9.86
Requires-Dist: aiohttp>=3.9.0
Requires-Dist: websockets>=14.0
Requires-Dist: pybit>=5.0.0
Requires-Dist: hyperliquid-python-sdk>=0.1.0
Requires-Dist: cryptography>=41.0.0
Requires-Dist: eth-account>=0.10.0
Requires-Dist: rich>=14.1.0
Requires-Dist: plotly>=5.0
Requires-Dist: tqdm>=4.65
Requires-Dist: ipywidgets>=8.0
Requires-Dist: nest-asyncio>=1.5
Requires-Dist: seaborn>=0.13.0
Requires-Dist: jinja2>=3.0.0
Requires-Dist: eventkit
Provides-Extra: test
Requires-Dist: tox; extra == "test"
Requires-Dist: pytest>=7.2.0; extra == "test"
Requires-Dist: pytest-cov>=3.0.0; extra == "test"
Requires-Dist: pytest-xdist>=2.5.0; extra == "test"
Requires-Dist: pytest-timeout>=1.4.2; extra == "test"
Requires-Dist: pytest-asyncio>=0.21.0; extra == "test"
Requires-Dist: parameterized>=0.6.1; extra == "test"
Requires-Dist: testfixtures>=4.1.2; extra == "test"
Requires-Dist: flake8>=3.9.1; extra == "test"
Requires-Dist: matplotlib>=1.5.3; extra == "test"
Requires-Dist: responses>=0.9.0; extra == "test"
Requires-Dist: freezegun>=1.2.0; extra == "test"
Requires-Dist: pandas-datareader>=0.2.1; extra == "test"
Requires-Dist: click; extra == "test"
Requires-Dist: coverage; extra == "test"
Requires-Dist: pytest-rerunfailures; extra == "test"
Requires-Dist: Cython<3.2.0,>=0.29.21; extra == "test"
Requires-Dist: pytest-benchmark>=5.1.0; extra == "test"
Requires-Dist: hypothesis>=6.0; extra == "test"
Provides-Extra: dev
Requires-Dist: pre-commit>=2.12.1; extra == "dev"
Requires-Dist: Cython>=0.29.21; extra == "dev"
Requires-Dist: ruff>=0.11.12; extra == "dev"
Requires-Dist: mypy>=1.10.0; extra == "dev"
Requires-Dist: black>=24.1; extra == "dev"
Requires-Dist: hypothesis>=6.0; extra == "dev"
Requires-Dist: twine>=6.0.0; extra == "dev"
Requires-Dist: jupyter>=1.0.0; extra == "dev"
Requires-Dist: jupyterlab>=4.0.0; extra == "dev"
Requires-Dist: ipython>=8.0.0; extra == "dev"
Requires-Dist: types-requests>=2.31.0; extra == "dev"
Requires-Dist: types-pytz>=2024.1.0; extra == "dev"
Requires-Dist: types-PyYAML>=6.0.12; extra == "dev"
Requires-Dist: pandas-stubs>=2.0.0; extra == "dev"
Requires-Dist: sqlalchemy-stubs>=0.4; extra == "dev"
Requires-Dist: types-python-dateutil>=2.8.19; extra == "dev"
Requires-Dist: types-networkx>=3.0; extra == "dev"
Requires-Dist: types-seaborn>=0.13.0; extra == "dev"
Provides-Extra: benchmarks
Requires-Dist: pytest-benchmark>=3.4.1; extra == "benchmarks"
Requires-Dist: memory_profiler>=0.61.0; extra == "benchmarks"
Requires-Dist: snakeviz>=2.2.0; extra == "benchmarks"
Requires-Dist: matplotlib>=3.5.0; extra == "benchmarks"
Provides-Extra: optimization
Requires-Dist: scikit-learn>=1.3.0; extra == "optimization"
Requires-Dist: scikit-optimize>=0.9.0; extra == "optimization"
Requires-Dist: deap>=1.4.0; extra == "optimization"
Requires-Dist: matplotlib>=3.5.0; extra == "optimization"
Requires-Dist: tqdm>=4.0.0; extra == "optimization"
Requires-Dist: psutil>=5.0.0; extra == "optimization"
Requires-Dist: hpbandster>=0.7.4; extra == "optimization"
Requires-Dist: ray[default]>=2.0.0; extra == "ray" and extra == "optimization"
Provides-Extra: docs
Requires-Dist: Cython; extra == "docs"
Requires-Dist: mkdocs>=1.5.0; extra == "docs"
Requires-Dist: mkdocs-material>=9.5.0; extra == "docs"
Requires-Dist: mkdocstrings[python]>=0.24.0; extra == "docs"
Requires-Dist: mkdocs-autorefs>=0.5.0; extra == "docs"
Requires-Dist: Sphinx>=1.3.2; extra == "docs"
Requires-Dist: numpydoc>=0.5.0; extra == "docs"
Requires-Dist: sphinx-autobuild>=0.6.0; extra == "docs"
Requires-Dist: pydata-sphinx-theme; extra == "docs"
Requires-Dist: sphinx_markdown_tables; extra == "docs"
Requires-Dist: m2r2; extra == "docs"
Provides-Extra: legacy
Requires-Dist: h5py>=2.7.1; extra == "legacy"
Requires-Dist: tables>=3.4.3; extra == "legacy"
Provides-Extra: full
Requires-Dist: rustybt[optimization]; extra == "full"
Requires-Dist: rustybt[benchmarks]; extra == "full"
Requires-Dist: rustybt[legacy]; extra == "full"
Provides-Extra: all
Requires-Dist: rustybt[optimization]; extra == "all"
Requires-Dist: rustybt[benchmarks]; extra == "all"
Requires-Dist: rustybt[legacy]; extra == "all"
Dynamic: license-file
